pypkgsbru/__init__.py
pypkgsbru/pypkgsbru.py
pypkgsbru-0.1.0.dist-info/LICENSE
pypkgsbru-0.1.0.dist-info/WHEEL
pypkgsbru-0.1.0.dist-info/METADATA
pypkgsbru-0.1.0.dist-info/RECORD
