Metadata-Version: 2.1
Name: pypkgsbru
Version: 0.1.0
Summary: 
Author: BruhatM
Author-email: bruhatm@outlook.com
Requires-Python: >=3.8,<4.0
Classifier: Programming Language :: Python :: 3
Classifier: Programming Language :: Python :: 3.8
Classifier: Programming Language :: Python :: 3.9
Requires-Dist: pandas (>=1.2.2,<2.0.0)
